cecresl.py
setup.py
cecstat.egg-info/PKG-INFO
cecstat.egg-info/SOURCES.txt
cecstat.egg-info/dependency_links.txt
cecstat.egg-info/top_level.txt