Metadata-Version: 1.0
Name: cecstat
Version: 1.0.0
Summary: A simple python module to auto-slove stupid statistic problem in class
Home-page: UNKNOWN
Author: cecliux
Author-email: src655@gmail.com
License: UNKNOWN
Platform: UNKNOWN
